{
    "os": "Linux-5.4.0-153-generic-x86_64-with-glibc2.31",
    "python": "3.10.13",
    "heartbeatAt": "2024-05-01T14:44:10.581340",
    "startedAt": "2024-05-01T14:44:09.901377",
    "docker": null,
    "cuda": null,
    "args": [],
    "state": "running",
    "program": "/raid/home/automathon_2024/account6/automathon-2024/run.py",
    "codePathLocal": "run.py",
    "codePath": "run.py",
    "git": {
        "remote": "git@github.com:Aelrach/automathon-2024.git",
        "commit": "5f0dfd8501d21a98e308216fed82cd5712f75afa"
    },
    "email": null,
    "root": "/raid/home/automathon_2024/account6/automathon-2024",
    "host": "dgxa100",
    "username": "account6",
    "executable": "/usr/bin/python",
    "cpu_count": 64,
    "cpu_count_logical": 128,
    "cpu_freq": {
        "current": 3189.130015625,
        "min": 1500.0,
        "max": 2250.0
    },
    "cpu_freq_per_core": [
        {
            "current": 3200.173,
            "min": 1500.0,
            "max": 2250.0
        },
        {
            "current": 3198.88,
            "min": 1500.0,
            "max": 2250.0
        },
        {
            "current": 3201.958,
            "min": 1500.0,
            "max": 2250.0
        },
        {
            "current": 3200.231,
            "min": 1500.0,
            "max": 2250.0
        },
        {
            "current": 3200.49,
            "min": 1500.0,
            "max": 2250.0
        },
        {
            "current": 3200.468,
            "min": 1500.0,
            "max": 2250.0
        },
        {
            "current": 3200.455,
            "min": 1500.0,
            "max": 2250.0
        },
        {
            "current": 3200.367,
            "min": 1500.0,
            "max": 2250.0
        },
        {
            "current": 3218.254,
            "min": 1500.0,
            "max": 2250.0
        },
        {
            "current": 3198.409,
            "min": 1500.0,
            "max": 2250.0
        },
        {
            "current": 3214.895,
            "min": 1500.0,
            "max": 2250.0
        },
        {
            "current": 3201.571,
            "min": 1500.0,
            "max": 2250.0
        },
        {
            "current": 3216.906,
            "min": 1500.0,
            "max": 2250.0
        },
        {
            "current": 3205.575,
            "min": 1500.0,
            "max": 2250.0
        },
        {
            "current": 3195.92,
            "min": 1500.0,
            "max": 2250.0
        },
        {
            "current": 3195.869,
            "min": 1500.0,
            "max": 2250.0
        },
        {
            "current": 3198.376,
            "min": 1500.0,
            "max": 2250.0
        },
        {
            "current": 3199.264,
            "min": 1500.0,
            "max": 2250.0
        },
        {
            "current": 3198.39,
            "min": 1500.0,
            "max": 2250.0
        },
        {
            "current": 3198.763,
            "min": 1500.0,
            "max": 2250.0
        },
        {
            "current": 3199.664,
            "min": 1500.0,
            "max": 2250.0
        },
        {
            "current": 3199.783,
            "min": 1500.0,
            "max": 2250.0
        },
        {
            "current": 3199.753,
            "min": 1500.0,
            "max": 2250.0
        },
        {
            "current": 3199.677,
            "min": 1500.0,
            "max": 2250.0
        },
        {
            "current": 3199.214,
            "min": 1500.0,
            "max": 2250.0
        },
        {
            "current": 3199.114,
            "min": 1500.0,
            "max": 2250.0
        },
        {
            "current": 3198.716,
            "min": 1500.0,
            "max": 2250.0
        },
        {
            "current": 3198.984,
            "min": 1500.0,
            "max": 2250.0
        },
        {
            "current": 3198.218,
            "min": 1500.0,
            "max": 2250.0
        },
        {
            "current": 3198.214,
            "min": 1500.0,
            "max": 2250.0
        },
        {
            "current": 3194.603,
            "min": 1500.0,
            "max": 2250.0
        },
        {
            "current": 3207.401,
            "min": 1500.0,
            "max": 2250.0
        },
        {
            "current": 3198.532,
            "min": 1500.0,
            "max": 2250.0
        },
        {
            "current": 3198.612,
            "min": 1500.0,
            "max": 2250.0
        },
        {
            "current": 3198.554,
            "min": 1500.0,
            "max": 2250.0
        },
        {
            "current": 3198.558,
            "min": 1500.0,
            "max": 2250.0
        },
        {
            "current": 3199.006,
            "min": 1500.0,
            "max": 2250.0
        },
        {
            "current": 3198.955,
            "min": 1500.0,
            "max": 2250.0
        },
        {
            "current": 3198.852,
            "min": 1500.0,
            "max": 2250.0
        },
        {
            "current": 3198.86,
            "min": 1500.0,
            "max": 2250.0
        },
        {
            "current": 3198.328,
            "min": 1500.0,
            "max": 2250.0
        },
        {
            "current": 3198.343,
            "min": 1500.0,
            "max": 2250.0
        },
        {
            "current": 3198.347,
            "min": 1500.0,
            "max": 2250.0
        },
        {
            "current": 3198.18,
            "min": 1500.0,
            "max": 2250.0
        },
        {
            "current": 3198.683,
            "min": 1500.0,
            "max": 2250.0
        },
        {
            "current": 3198.616,
            "min": 1500.0,
            "max": 2250.0
        },
        {
            "current": 3198.593,
            "min": 1500.0,
            "max": 2250.0
        },
        {
            "current": 3197.367,
            "min": 1500.0,
            "max": 2250.0
        },
        {
            "current": 3212.872,
            "min": 1500.0,
            "max": 2250.0
        },
        {
            "current": 3198.031,
            "min": 1500.0,
            "max": 2250.0
        },
        {
            "current": 3211.352,
            "min": 1500.0,
            "max": 2250.0
        },
        {
            "current": 3216.979,
            "min": 1500.0,
            "max": 2250.0
        },
        {
            "current": 3199.396,
            "min": 1500.0,
            "max": 2250.0
        },
        {
            "current": 3200.302,
            "min": 1500.0,
            "max": 2250.0
        },
        {
            "current": 3199.829,
            "min": 1500.0,
            "max": 2250.0
        },
        {
            "current": 3199.758,
            "min": 1500.0,
            "max": 2250.0
        },
        {
            "current": 3191.269,
            "min": 1500.0,
            "max": 2250.0
        },
        {
            "current": 3200.866,
            "min": 1500.0,
            "max": 2250.0
        },
        {
            "current": 3199.904,
            "min": 1500.0,
            "max": 2250.0
        },
        {
            "current": 3199.898,
            "min": 1500.0,
            "max": 2250.0
        },
        {
            "current": 3202.093,
            "min": 1500.0,
            "max": 2250.0
        },
        {
            "current": 1595.626,
            "min": 1500.0,
            "max": 2250.0
        },
        {
            "current": 3202.029,
            "min": 1500.0,
            "max": 2250.0
        },
        {
            "current": 2376.592,
            "min": 1500.0,
            "max": 2250.0
        },
        {
            "current": 3199.691,
            "min": 1500.0,
            "max": 2250.0
        },
        {
            "current": 3199.575,
            "min": 1500.0,
            "max": 2250.0
        },
        {
            "current": 3201.837,
            "min": 1500.0,
            "max": 2250.0
        },
        {
            "current": 3206.101,
            "min": 1500.0,
            "max": 2250.0
        },
        {
            "current": 3200.12,
            "min": 1500.0,
            "max": 2250.0
        },
        {
            "current": 3200.232,
            "min": 1500.0,
            "max": 2250.0
        },
        {
            "current": 3200.298,
            "min": 1500.0,
            "max": 2250.0
        },
        {
            "current": 3200.302,
            "min": 1500.0,
            "max": 2250.0
        },
        {
            "current": 3200.432,
            "min": 1500.0,
            "max": 2250.0
        },
        {
            "current": 3140.914,
            "min": 1500.0,
            "max": 2250.0
        },
        {
            "current": 3198.484,
            "min": 1500.0,
            "max": 2250.0
        },
        {
            "current": 3198.746,
            "min": 1500.0,
            "max": 2250.0
        },
        {
            "current": 3197.715,
            "min": 1500.0,
            "max": 2250.0
        },
        {
            "current": 3178.01,
            "min": 1500.0,
            "max": 2250.0
        },
        {
            "current": 3197.681,
            "min": 1500.0,
            "max": 2250.0
        },
        {
            "current": 3197.638,
            "min": 1500.0,
            "max": 2250.0
        },
        {
            "current": 3201.981,
            "min": 1500.0,
            "max": 2250.0
        },
        {
            "current": 3200.075,
            "min": 1500.0,
            "max": 2250.0
        },
        {
            "current": 3200.224,
            "min": 1500.0,
            "max": 2250.0
        },
        {
            "current": 3196.903,
            "min": 1500.0,
            "max": 2250.0
        },
        {
            "current": 3200.621,
            "min": 1500.0,
            "max": 2250.0
        },
        {
            "current": 3201.203,
            "min": 1500.0,
            "max": 2250.0
        },
        {
            "current": 3201.164,
            "min": 1500.0,
            "max": 2250.0
        },
        {
            "current": 3201.073,
            "min": 1500.0,
            "max": 2250.0
        },
        {
            "current": 3200.655,
            "min": 1500.0,
            "max": 2250.0
        },
        {
            "current": 3200.587,
            "min": 1500.0,
            "max": 2250.0
        },
        {
            "current": 3200.163,
            "min": 1500.0,
            "max": 2250.0
        },
        {
            "current": 3200.39,
            "min": 1500.0,
            "max": 2250.0
        },
        {
            "current": 3199.424,
            "min": 1500.0,
            "max": 2250.0
        },
        {
            "current": 3199.368,
            "min": 1500.0,
            "max": 2250.0
        },
        {
            "current": 3199.101,
            "min": 1500.0,
            "max": 2250.0
        },
        {
            "current": 3198.954,
            "min": 1500.0,
            "max": 2250.0
        },
        {
            "current": 3199.938,
            "min": 1500.0,
            "max": 2250.0
        },
        {
            "current": 3200.062,
            "min": 1500.0,
            "max": 2250.0
        },
        {
            "current": 3199.965,
            "min": 1500.0,
            "max": 2250.0
        },
        {
            "current": 3200.041,
            "min": 1500.0,
            "max": 2250.0
        },
        {
            "current": 3200.44,
            "min": 1500.0,
            "max": 2250.0
        },
        {
            "current": 3200.384,
            "min": 1500.0,
            "max": 2250.0
        },
        {
            "current": 3200.295,
            "min": 1500.0,
            "max": 2250.0
        },
        {
            "current": 3200.284,
            "min": 1500.0,
            "max": 2250.0
        },
        {
            "current": 3199.758,
            "min": 1500.0,
            "max": 2250.0
        },
        {
            "current": 3199.777,
            "min": 1500.0,
            "max": 2250.0
        },
        {
            "current": 3199.791,
            "min": 1500.0,
            "max": 2250.0
        },
        {
            "current": 3199.607,
            "min": 1500.0,
            "max": 2250.0
        },
        {
            "current": 3200.092,
            "min": 1500.0,
            "max": 2250.0
        },
        {
            "current": 3200.015,
            "min": 1500.0,
            "max": 2250.0
        },
        {
            "current": 3199.994,
            "min": 1500.0,
            "max": 2250.0
        },
        {
            "current": 3198.75,
            "min": 1500.0,
            "max": 2250.0
        },
        {
            "current": 3201.786,
            "min": 1500.0,
            "max": 2250.0
        },
        {
            "current": 3199.464,
            "min": 1500.0,
            "max": 2250.0
        },
        {
            "current": 3201.738,
            "min": 1500.0,
            "max": 2250.0
        },
        {
            "current": 3201.591,
            "min": 1500.0,
            "max": 2250.0
        },
        {
            "current": 3218.033,
            "min": 1500.0,
            "max": 2250.0
        },
        {
            "current": 3201.748,
            "min": 1500.0,
            "max": 2250.0
        },
        {
            "current": 3203.798,
            "min": 1500.0,
            "max": 2250.0
        },
        {
            "current": 3212.043,
            "min": 1500.0,
            "max": 2250.0
        },
        {
            "current": 3200.755,
            "min": 1500.0,
            "max": 2250.0
        },
        {
            "current": 3199.079,
            "min": 1500.0,
            "max": 2250.0
        },
        {
            "current": 3199.032,
            "min": 1500.0,
            "max": 2250.0
        },
        {
            "current": 3201.154,
            "min": 1500.0,
            "max": 2250.0
        },
        {
            "current": 3190.999,
            "min": 1500.0,
            "max": 2250.0
        },
        {
            "current": 2381.57,
            "min": 1500.0,
            "max": 2250.0
        },
        {
            "current": 3206.067,
            "min": 1500.0,
            "max": 2250.0
        },
        {
            "current": 2354.677,
            "min": 1500.0,
            "max": 2250.0
        }
    ],
    "disk": {
        "/": {
            "total": 1757.8785285949707,
            "used": 376.17148208618164
        }
    },
    "memory": {
        "total": 503.7273750305176
    }
}
